CHANGELOG.rst
LICENSE.txt
MANIFEST.in
README.rst
setup.cfg
setup.py
docs/Makefile
docs/changes.rst
docs/conf.py
docs/generating.rst
docs/glossary.rst
docs/index.rst
docs/introduction.rst
docs/porting.rst
docs/restful.rst
docs/routes-logo.png
docs/setting_up.rst
docs/todo.rst
docs/uni_redirect_rest.rst
docs/modules/index.rst
docs/modules/lru.rst
docs/modules/mapper.rst
docs/modules/middleware.rst
docs/modules/route.rst
docs/modules/routes.rst
docs/modules/util.rst
docs/src/README
docs/src/routes-logo-boehme.svg
pybald_routes.egg-info/PKG-INFO
pybald_routes.egg-info/SOURCES.txt
pybald_routes.egg-info/dependency_links.txt
pybald_routes.egg-info/not-zip-safe
pybald_routes.egg-info/requires.txt
pybald_routes.egg-info/top_level.txt
routes/__init__.py
routes/base.py
routes/mapper.py
routes/middleware.py
routes/route.py
routes/util.py