Metadata-Version: 1.1
Name: pybald-routes
Version: 2.11
Summary: Routing Recognition and Generation Tools
Home-page: https://github.com/mikepk/routes
Author: Michael Kowalchik
Author-email: mikepk@tenzerolab.com
License: MIT
Keywords: pybald routes webob dispatch
Platform: UNKNOWN
Classifier: Development Status :: 5 - Production/Stable
Classifier: Intended Audience :: Developers
Classifier: License :: OSI Approved :: BSD License
Classifier: Topic :: Internet :: WWW/HTTP
Classifier: Topic :: Software Development :: Libraries :: Python Modules
Classifier: Programming Language :: Python
Classifier: Programming Language :: Python :: 2
Classifier: Programming Language :: Python :: 2.6
Classifier: Programming Language :: Python :: 2.7
Classifier: Programming Language :: Python :: 3
Classifier: Programming Language :: Python :: 3.2
Classifier: Programming Language :: Python :: 3.3
